cheshire/__init__.py
cheshire/cli.py
cheshire/dummy.py
cheshire/package_data/__init__.py
catalystcoop.cheshire-0.4.1.dist-info/LICENSE.txt
catalystcoop.cheshire-0.4.1.dist-info/METADATA
catalystcoop.cheshire-0.4.1.dist-info/WHEEL
catalystcoop.cheshire-0.4.1.dist-info/entry_points.txt
catalystcoop.cheshire-0.4.1.dist-info/top_level.txt
catalystcoop.cheshire-0.4.1.dist-info/RECORD
