Metadata-Version: 2.1
Name: catalystcoop.cheshire
Version: 0.4.1
Summary: Replace this text with a one line description of the package.
Author-email: Catalyst Cooperative <pudl@catalyst.coop>
License: MIT License
Project-URL: Source, https://github.com/catalyst-cooperative/cheshire
Project-URL: Documentation, https://catalystcoop-cheshire.readthedocs.io
Project-URL: Issue Tracker, https://github.com/catalyst-cooperative/cheshire/issues
Keywords: template,testing,linting,github actions,continuous integration,continuous delivery
Classifier: Development Status :: 3 - Alpha
Classifier: Environment :: Console
Classifier: License :: OSI Approved :: MIT License
Classifier: Natural Language :: English
Classifier: Operating System :: OS Independent
Classifier: Programming Language :: Python
Classifier: Programming Language :: Python :: 3
Classifier: Programming Language :: Python :: 3 :: Only
Classifier: Programming Language :: Python :: 3.10
Classifier: Programming Language :: Python :: 3.11
Requires-Python: <3.12,>=3.10
License-File: LICENSE.txt
Requires-Dist: pandas[compression,excel,fss,gcp,parquet] <3,>=2
Requires-Dist: pydantic[email] <3,>=2
Requires-Dist: sqlalchemy <3,>=2
Provides-Extra: dev
Requires-Dist: build <2,>=1 ; extra == 'dev'
Requires-Dist: black <24,>=22 ; extra == 'dev'
Requires-Dist: tox <5,>=4 ; extra == 'dev'
Requires-Dist: twine <5,>=4 ; extra == 'dev'
Provides-Extra: docs
Requires-Dist: doc8 <2,>=1 ; extra == 'docs'
Requires-Dist: furo >=2022.4.7 ; extra == 'docs'
Requires-Dist: sphinx <8,>=6 ; extra == 'docs'
Requires-Dist: sphinx-autoapi <3,>=2 ; extra == 'docs'
Requires-Dist: sphinx-issues <2,>=1.2 ; extra == 'docs'
Provides-Extra: tests
Requires-Dist: coverage <8,>=7 ; extra == 'tests'
Requires-Dist: exceptiongroup <2,>=1 ; extra == 'tests'
Requires-Dist: jupyter ; extra == 'tests'
Requires-Dist: mypy <1.6,>=1.0 ; extra == 'tests'
Requires-Dist: nbconvert <8,>=7 ; extra == 'tests'
Requires-Dist: nbformat <6,>=5 ; extra == 'tests'
Requires-Dist: pre-commit <4,>=3 ; extra == 'tests'
Requires-Dist: pydocstyle <7,>=6 ; extra == 'tests'
Requires-Dist: pytest-console-scripts <2,>=1.1 ; extra == 'tests'
Requires-Dist: pytest-cov <5,>=4 ; extra == 'tests'
Requires-Dist: pytest <8,>=7 ; extra == 'tests'
Requires-Dist: ruff >=0.0.290 ; extra == 'tests'
Requires-Dist: tox <5,>=4 ; extra == 'tests'
Provides-Extra: types
Requires-Dist: types-setuptools ; extra == 'types'
